inductor/__init__.py
inductor/auth_session.py
inductor/config.py
inductor/quality.py
inductor/backend_client/__init__.py
inductor/backend_client/backend_client.py
inductor/backend_client/wire_model.py
inductor/cli/__init__.py
inductor/cli/cli.py
inductor/cli/questions.py
inductor/data_model/__init__.py
inductor/data_model/data_model.py
inductor/execution/__init__.py
inductor/execution/execution.py
inductor/execution/live_execution.py
inductor/execution/playground_execution.py
inductor/execution/quality_measure_execution.py
inductor/execution/test_suite_execution.py
inductor-0.3.83.dist-info/METADATA
inductor-0.3.83.dist-info/WHEEL
inductor-0.3.83.dist-info/entry_points.txt
inductor-0.3.83.dist-info/RECORD
