Metadata-Version: 2.3
Name: inductor
Version: 0.3.83
Summary: The Inductor CLI and client library
Project-URL: Homepage, https://inductor.ai
Classifier: Programming Language :: Python :: 3
Requires-Python: >=3.7
Requires-Dist: auth0-python<5,>=4.4.2
Requires-Dist: httpx<1,>=0.25.0
Requires-Dist: inquirer<4,>=3.1.3
Requires-Dist: openai<2,>=1.0.0
Requires-Dist: pydantic-core<3,>=2.22.0
Requires-Dist: pydantic-settings==2.1.0
Requires-Dist: pydantic<3,>=2.4.2
Requires-Dist: python-multipart<1,>=0.0.6
Requires-Dist: pyyaml<7,>=6.0.1
Requires-Dist: requests<3,>=2.31.0
Requires-Dist: tiktoken<1,>=0.5.2
Requires-Dist: typer[all]<1,>=0.9.0
Requires-Dist: typing-extensions<5,>=4.8.0
Requires-Dist: watchfiles<1,>=0.20.0
Requires-Dist: websockets<12,>=11.0.3
